pyprojroot/__init__.py
pyprojroot/criterion.py
pyprojroot/here.py
pyprojroot/py.typed
pyprojroot/pyprojroot.py
pyprojroot/root.py
pyprojroot-0.3.0.dist-info/LICENSE
pyprojroot-0.3.0.dist-info/METADATA
pyprojroot-0.3.0.dist-info/WHEEL
pyprojroot-0.3.0.dist-info/top_level.txt
pyprojroot-0.3.0.dist-info/RECORD
