Metadata-Version: 2.1
Name: pyprojroot
Version: 0.3.0
Summary: Project-oriented workflow in Python
Author-email: Daniel Chen <chendaniely@gmail.com>
Project-URL: Homepage, https://github.com/chendaniely/pyprojroot
Project-URL: Bug Tracker, https://github.com/chendaniely/pyprojroot/issues
Classifier: Programming Language :: Python :: 3
Classifier: License :: OSI Approved :: MIT License
Classifier: Operating System :: OS Independent
Requires-Python: >=3.7
License-File: LICENSE
